<?xml version="1.0" encoding="UTF-8" standalone="yes"?>
<PopulateCache async="false" continueOnError="false" enabled="true" name="Populate-Product-List">
    <DisplayName>Populate Product List</DisplayName>
    <Properties/>
    <CacheKey>
        <KeyFragment ref="request.uri"/>
        <KeyFragment ref="request.queryparam.types"/>
    </CacheKey>
    <CacheResource>remote-service</CacheResource>
    <Scope>Exclusive</Scope>
    <ExpirySettings>
        <TimeoutInSec>120</TimeoutInSec>
    </ExpirySettings>
    <Source>prodcache</Source>
</PopulateCache>
